tengen/__init__.py
tengen/cli.py
tengen/template.py
tengen-0.1.6.dist-info/LICENSE
tengen-0.1.6.dist-info/METADATA
tengen-0.1.6.dist-info/WHEEL
tengen-0.1.6.dist-info/entry_points.txt
tengen-0.1.6.dist-info/top_level.txt
tengen-0.1.6.dist-info/RECORD
