Metadata-Version: 2.1
Name: tengen
Version: 0.1.6
Summary: Generate string using template
Author-email: mskz-3110 <mskz.saito@gmail.com>
Project-URL: Homepage, https://github.com/mskz-3110/tengen
Project-URL: Issues, https://github.com/mskz-3110/tengen/issues
Classifier: Programming Language :: Python :: 3
Classifier: License :: OSI Approved :: MIT License
Classifier: Operating System :: OS Independent
Requires-Python: >=3.13
License-File: LICENSE
Requires-Dist: pyemon
